{
"graph": {
"edges": [
    {
        "data": {
            "id": "010y-035p",
            "source": "010y",
            "target": "035p",
            "width": 5.327546151333821
        }
    },
    {
        "data": {
            "id": "010y-035r",
            "source": "010y",
            "target": "035r",
            "width": 1.9459101490553132
        }
    },
    {
        "data": {
            "id": "010y-047p",
            "source": "010y",
            "target": "047p",
            "width": 2.833213344056216
        }
    },
    {
        "data": {
            "id": "010y-064p",
            "source": "010y",
            "target": "064p",
            "width": 5.516500392221337
        }
    },
    {
        "data": {
            "id": "010y-038p",
            "source": "010y",
            "target": "038p",
            "width": 5.693295484792039
        }
    },
    {
        "data": {
            "id": "010y-043p",
            "source": "010y",
            "target": "043p",
            "width": 5.750406198543213
        }
    },
    {
        "data": {
            "id": "010y-016p",
            "source": "010y",
            "target": "016p",
            "width": 5.577839464566269
        }
    },
    {
        "data": {
            "id": "010y-043w",
            "source": "010y",
            "target": "043w",
            "width": 2.04717228111105
        }
    },
    {
        "data": {
            "id": "010y-061y",
            "source": "010y",
            "target": "061y",
            "width": 5.349110316924943
        }
    },
    {
        "data": {
            "id": "010y-058y",
            "source": "010y",
            "target": "058y",
            "width": 5.562129237568972
        }
    },
    {
        "data": {
            "id": "010y-044p",
            "source": "010y",
            "target": "044p",
            "width": 5.5088717525961295
        }
    },
    {
        "data": {
            "id": "038r-040r",
            "source": "038r",
            "target": "040r",
            "width": 1.3862943611198906
        }
    },
    {
        "data": {
            "id": "038r-052w",
            "source": "038r",
            "target": "052w",
            "width": 3.1858059236159284
        }
    },
    {
        "data": {
            "id": "038r-051p",
            "source": "038r",
            "target": "051p",
            "width": 3.7424651416448307
        }
    },
    {
        "data": {
            "id": "038r-013p",
            "source": "038r",
            "target": "013p",
            "width": 2.789864912993111
        }
    },
    {
        "data": {
            "id": "038r-020y",
            "source": "038r",
            "target": "020y",
            "width": 4.216797083769962
        }
    },
    {
        "data": {
            "id": "038r-045p",
            "source": "038r",
            "target": "045p",
            "width": 4.377395881850016
        }
    },
    {
        "data": {
            "id": "038p-035p",
            "source": "038p",
            "target": "035p",
            "width": 5.613520887229914
        }
    },
    {
        "data": {
            "id": "038p-047p",
            "source": "038p",
            "target": "047p",
            "width": 3.022502657018006
        }
    },
    {
        "data": {
            "id": "038p-064p",
            "source": "038p",
            "target": "064p",
            "width": 5.582881141654426
        }
    },
    {
        "data": {
            "id": "038p-044p",
            "source": "038p",
            "target": "044p",
            "width": 5.599079962054353
        }
    },
    {
        "data": {
            "id": "038p-016p",
            "source": "038p",
            "target": "016p",
            "width": 5.658662060414521
        }
    },
    {
        "data": {
            "id": "038p-061y",
            "source": "038p",
            "target": "061y",
            "width": 5.454498611470957
        }
    },
    {
        "data": {
            "id": "038p-043p",
            "source": "038p",
            "target": "043p",
            "width": 6.01720899723572
        }
    },
    {
        "data": {
            "id": "038p-058y",
            "source": "038p",
            "target": "058y",
            "width": 5.776836928390935
        }
    },
    {
        "data": {
            "id": "038p-046p",
            "source": "038p",
            "target": "046p",
            "width": 2.282174095733918
        }
    },
    {
        "data": {
            "id": "038p-008p",
            "source": "038p",
            "target": "008p",
            "width": 3.7072864406752943
        }
    },
    {
        "data": {
            "id": "048p-011y",
            "source": "048p",
            "target": "011y",
            "width": 1.8444397270569681
        }
    },
    {
        "data": {
            "id": "048p-018p",
            "source": "048p",
            "target": "018p",
            "width": 1.3195286648076292
        }
    },
    {
        "data": {
            "id": "048p-037w",
            "source": "048p",
            "target": "037w",
            "width": 5.337341572896185
        }
    },
    {
        "data": {
            "id": "048p-024y",
            "source": "048p",
            "target": "024y",
            "width": 3.8267474548306266
        }
    },
    {
        "data": {
            "id": "048p-049p",
            "source": "048p",
            "target": "049p",
            "width": 5.389301030245767
        }
    },
    {
        "data": {
            "id": "048p-070y",
            "source": "048p",
            "target": "070y",
            "width": 5.642133366483955
        }
    },
    {
        "data": {
            "id": "048p-012b",
            "source": "048p",
            "target": "012b",
            "width": 3.306020517416546
        }
    },
    {
        "data": {
            "id": "048p-020p",
            "source": "048p",
            "target": "020p",
            "width": 4.872773182233776
        }
    },
    {
        "data": {
            "id": "048p-058y",
            "source": "048p",
            "target": "058y",
            "width": 0.34657359027997264
        }
    },
    {
        "data": {
            "id": "048p-008p",
            "source": "048p",
            "target": "008p",
            "width": 4.712604893419074
        }
    },
    {
        "data": {
            "id": "048p-047p",
            "source": "048p",
            "target": "047p",
            "width": 1.151292546497023
        }
    },
    {
        "data": {
            "id": "016p-035p",
            "source": "016p",
            "target": "035p",
            "width": 5.33776916534577
        }
    },
    {
        "data": {
            "id": "016p-054w",
            "source": "016p",
            "target": "054w",
            "width": 1.9250738008550292
        }
    },
    {
        "data": {
            "id": "016p-044p",
            "source": "016p",
            "target": "044p",
            "width": 5.578253815416541
        }
    },
    {
        "data": {
            "id": "016p-064p",
            "source": "016p",
            "target": "064p",
            "width": 5.51884609245368
        }
    },
    {
        "data": {
            "id": "016p-043p",
            "source": "016p",
            "target": "043p",
            "width": 5.851264389318663
        }
    },
    {
        "data": {
            "id": "016p-043w",
            "source": "016p",
            "target": "043w",
            "width": 0.5493061443340549
        }
    },
    {
        "data": {
            "id": "016p-061y",
            "source": "016p",
            "target": "061y",
            "width": 5.5323416637530025
        }
    },
    {
        "data": {
            "id": "016p-063p",
            "source": "016p",
            "target": "063p",
            "width": 0.5493061443340549
        }
    },
    {
        "data": {
            "id": "016p-058y",
            "source": "016p",
            "target": "058y",
            "width": 5.403295861303054
        }
    },
    {
        "data": {
            "id": "016p-046p",
            "source": "016p",
            "target": "046p",
            "width": 3.009296607248117
        }
    },
    {
        "data": {
            "id": "016p-008p",
            "source": "016p",
            "target": "008p",
            "width": 1.9659128163621629
        }
    },
    {
        "data": {
            "id": "016p-047p",
            "source": "016p",
            "target": "047p",
            "width": 2.9010591876885314
        }
    },
    {
        "data": {
            "id": "010p-052w",
            "source": "010p",
            "target": "052w",
            "width": 4.832583454811036
        }
    },
    {
        "data": {
            "id": "010p-011y",
            "source": "010p",
            "target": "011y",
            "width": 0.5493061443340549
        }
    },
    {
        "data": {
            "id": "010p-051p",
            "source": "010p",
            "target": "051p",
            "width": 3.9704698811638957
        }
    },
    {
        "data": {
            "id": "010p-013p",
            "source": "010p",
            "target": "013p",
            "width": 2.152032546602085
        }
    },
    {
        "data": {
            "id": "010p-009p",
            "source": "010p",
            "target": "009p",
            "width": 1.0397207708399179
        }
    },
    {
        "data": {
            "id": "010p-020y",
            "source": "010p",
            "target": "020y",
            "width": 4.636516720657303
        }
    },
    {
        "data": {
            "id": "012b-054w",
            "source": "012b",
            "target": "054w",
            "width": 4.00782880727867
        }
    },
    {
        "data": {
            "id": "012b-052w",
            "source": "012b",
            "target": "052w",
            "width": 0.8047189562170501
        }
    },
    {
        "data": {
            "id": "012b-018p",
            "source": "012b",
            "target": "018p",
            "width": 6.139937964206846
        }
    },
    {
        "data": {
            "id": "012b-037w",
            "source": "012b",
            "target": "037w",
            "width": 4.508438487381691
        }
    },
    {
        "data": {
            "id": "012b-011y",
            "source": "012b",
            "target": "011y",
            "width": 3.3205910848702955
        }
    },
    {
        "data": {
            "id": "012b-056b",
            "source": "012b",
            "target": "056b",
            "width": 3.242317617817626
        }
    },
    {
        "data": {
            "id": "012b-055b",
            "source": "012b",
            "target": "055b",
            "width": 4.789467002654221
        }
    },
    {
        "data": {
            "id": "012b-070y",
            "source": "012b",
            "target": "070y",
            "width": 5.246622248691769
        }
    },
    {
        "data": {
            "id": "012b-020p",
            "source": "012b",
            "target": "020p",
            "width": 4.298833287783057
        }
    },
    {
        "data": {
            "id": "012b-008p",
            "source": "012b",
            "target": "008p",
            "width": 2.934648456566887
        }
    },
    {
        "data": {
            "id": "067p-040r",
            "source": "067p",
            "target": "040r",
            "width": 4.08763305205603
        }
    },
    {
        "data": {
            "id": "067p-011y",
            "source": "067p",
            "target": "011y",
            "width": 4.89953551780785
        }
    },
    {
        "data": {
            "id": "067p-014p",
            "source": "067p",
            "target": "014p",
            "width": 4.832583454811036
        }
    },
    {
        "data": {
            "id": "067p-015p",
            "source": "067p",
            "target": "015p",
            "width": 4.4641876299268155
        }
    },
    {
        "data": {
            "id": "067p-046p",
            "source": "067p",
            "target": "046p",
            "width": 4.257996235419859
        }
    },
    {
        "data": {
            "id": "067p-009p",
            "source": "067p",
            "target": "009p",
            "width": 4.150264303099869
        }
    },
    {
        "data": {
            "id": "051p-045p",
            "source": "051p",
            "target": "045p",
            "width": 3.0044065927212973
        }
    },
    {
        "data": {
            "id": "051p-020y",
            "source": "051p",
            "target": "020y",
            "width": 1.4451858789480823
        }
    },
    {
        "data": {
            "id": "035p-044p",
            "source": "035p",
            "target": "044p",
            "width": 5.352666087508732
        }
    },
    {
        "data": {
            "id": "035p-064p",
            "source": "035p",
            "target": "064p",
            "width": 5.432500092565598
        }
    },
    {
        "data": {
            "id": "035p-043p",
            "source": "035p",
            "target": "043p",
            "width": 5.824693156274282
        }
    },
    {
        "data": {
            "id": "035p-043w",
            "source": "035p",
            "target": "043w",
            "width": 2.1847239262335107
        }
    },
    {
        "data": {
            "id": "035p-061y",
            "source": "035p",
            "target": "061y",
            "width": 5.482423927750674
        }
    },
    {
        "data": {
            "id": "035p-063p",
            "source": "035p",
            "target": "063p",
            "width": 0.8958797346140275
        }
    },
    {
        "data": {
            "id": "035p-058y",
            "source": "035p",
            "target": "058y",
            "width": 5.717681921760922
        }
    },
    {
        "data": {
            "id": "035p-046p",
            "source": "035p",
            "target": "046p",
            "width": 2.7035858857300594
        }
    },
    {
        "data": {
            "id": "035p-008p",
            "source": "035p",
            "target": "008p",
            "width": 2.4779135288006304
        }
    },
    {
        "data": {
            "id": "035p-050g",
            "source": "035p",
            "target": "050g",
            "width": 1.9250738008550292
        }
    },
    {
        "data": {
            "id": "035p-047p",
            "source": "035p",
            "target": "047p",
            "width": 2.6922475313945444
        }
    },
    {
        "data": {
            "id": "035r-054w",
            "source": "035r",
            "target": "054w",
            "width": 1.791759469228055
        }
    },
    {
        "data": {
            "id": "035r-008p",
            "source": "035r",
            "target": "008p",
            "width": 3.247632777968504
        }
    },
    {
        "data": {
            "id": "035r-047p",
            "source": "035r",
            "target": "047p",
            "width": 3.545038417888046
        }
    },
    {
        "data": {
            "id": "047p-018p",
            "source": "047p",
            "target": "018p",
            "width": 0.34657359027997264
        }
    },
    {
        "data": {
            "id": "047p-037w",
            "source": "047p",
            "target": "037w",
            "width": 2.4849066497880004
        }
    },
    {
        "data": {
            "id": "047p-049w",
            "source": "047p",
            "target": "049w",
            "width": 4.061037187681109
        }
    },
    {
        "data": {
            "id": "047p-061y",
            "source": "047p",
            "target": "061y",
            "width": 1.4722194895832201
        }
    },
    {
        "data": {
            "id": "047p-044p",
            "source": "047p",
            "target": "044p",
            "width": 2.30756025842063
        }
    },
    {
        "data": {
            "id": "047p-043p",
            "source": "047p",
            "target": "043p",
            "width": 2.1972245773362196
        }
    },
    {
        "data": {
            "id": "047p-058y",
            "source": "047p",
            "target": "058y",
            "width": 2.3124864066421353
        }
    },
    {
        "data": {
            "id": "047p-046p",
            "source": "047p",
            "target": "046p",
            "width": 6.245732925261109
        }
    },
    {
        "data": {
            "id": "047p-008p",
            "source": "047p",
            "target": "008p",
            "width": 6.067927011558702
        }
    },
    {
        "data": {
            "id": "047p-103w",
            "source": "047p",
            "target": "103w",
            "width": 4.337781763693839
        }
    },
    {
        "data": {
            "id": "064p-044p",
            "source": "064p",
            "target": "044p",
            "width": 5.432996854103623
        }
    },
    {
        "data": {
            "id": "064p-043p",
            "source": "064p",
            "target": "043p",
            "width": 5.607158626192447
        }
    },
    {
        "data": {
            "id": "064p-061y",
            "source": "064p",
            "target": "061y",
            "width": 5.245373150168377
        }
    },
    {
        "data": {
            "id": "064p-058y",
            "source": "064p",
            "target": "058y",
            "width": 5.382777192099918
        }
    },
    {
        "data": {
            "id": "064p-008p",
            "source": "064p",
            "target": "008p",
            "width": 1.4978661367769954
        }
    },
    {
        "data": {
            "id": "055b-040r",
            "source": "055b",
            "target": "040r",
            "width": 1.1989476363991853
        }
    },
    {
        "data": {
            "id": "055b-024y",
            "source": "055b",
            "target": "024y",
            "width": 5.136144338136351
        }
    },
    {
        "data": {
            "id": "055b-018p",
            "source": "055b",
            "target": "018p",
            "width": 5.088700130450955
        }
    },
    {
        "data": {
            "id": "055b-037w",
            "source": "055b",
            "target": "037w",
            "width": 2.3767950955531822
        }
    },
    {
        "data": {
            "id": "055b-011y",
            "source": "055b",
            "target": "011y",
            "width": 0.6931471805599453
        }
    },
    {
        "data": {
            "id": "055b-054w",
            "source": "055b",
            "target": "054w",
            "width": 2.2154083994216567
        }
    },
    {
        "data": {
            "id": "055b-056b",
            "source": "055b",
            "target": "056b",
            "width": 4.843038766534839
        }
    },
    {
        "data": {
            "id": "055b-070y",
            "source": "055b",
            "target": "070y",
            "width": 4.560153124636101
        }
    },
    {
        "data": {
            "id": "055b-020p",
            "source": "055b",
            "target": "020p",
            "width": 5.286081360585793
        }
    },
    {
        "data": {
            "id": "055b-008p",
            "source": "055b",
            "target": "008p",
            "width": 2.6182209814149746
        }
    },
    {
        "data": {
            "id": "055b-020y",
            "source": "055b",
            "target": "020y",
            "width": 0.8047189562170501
        }
    },
    {
        "data": {
            "id": "037w-054w",
            "source": "037w",
            "target": "054w",
            "width": 5.856703071190046
        }
    },
    {
        "data": {
            "id": "037w-011y",
            "source": "037w",
            "target": "011y",
            "width": 1.3862943611198906
        }
    },
    {
        "data": {
            "id": "037w-052w",
            "source": "037w",
            "target": "052w",
            "width": 0.34657359027997264
        }
    },
    {
        "data": {
            "id": "037w-018p",
            "source": "037w",
            "target": "018p",
            "width": 1.151292546497023
        }
    },
    {
        "data": {
            "id": "037w-024y",
            "source": "037w",
            "target": "024y",
            "width": 3.605039814085394
        }
    },
    {
        "data": {
            "id": "037w-049p",
            "source": "037w",
            "target": "049p",
            "width": 5.15751706548008
        }
    },
    {
        "data": {
            "id": "037w-070y",
            "source": "037w",
            "target": "070y",
            "width": 5.260227693178628
        }
    },
    {
        "data": {
            "id": "037w-020p",
            "source": "037w",
            "target": "020p",
            "width": 3.243842009242305
        }
    },
    {
        "data": {
            "id": "037w-058y",
            "source": "037w",
            "target": "058y",
            "width": 2.5407021824922316
        }
    },
    {
        "data": {
            "id": "037w-008p",
            "source": "037w",
            "target": "008p",
            "width": 4.838073854545255
        }
    },
    {
        "data": {
            "id": "082w-050y",
            "source": "082w",
            "target": "050y",
            "width": 0.6931471805599453
        }
    },
    {
        "data": {
            "id": "082w-034p",
            "source": "082w",
            "target": "034p",
            "width": 0.5493061443340549
        }
    },
    {
        "data": {
            "id": "082w-043w",
            "source": "082w",
            "target": "043w",
            "width": 5.504355635395946
        }
    },
    {
        "data": {
            "id": "082w-067y",
            "source": "082w",
            "target": "067y",
            "width": 1.4722194895832201
        }
    },
    {
        "data": {
            "id": "082w-062p",
            "source": "082w",
            "target": "062p",
            "width": 5.5280256331483555
        }
    },
    {
        "data": {
            "id": "082w-063p",
            "source": "082w",
            "target": "063p",
            "width": 5.723312696606498
        }
    },
    {
        "data": {
            "id": "082w-050g",
            "source": "082w",
            "target": "050g",
            "width": 5.49142453080605
        }
    },
    {
        "data": {
            "id": "043w-061y",
            "source": "043w",
            "target": "061y",
            "width": 0.8958797346140275
        }
    },
    {
        "data": {
            "id": "043w-063p",
            "source": "043w",
            "target": "063p",
            "width": 5.5987373601854165
        }
    },
    {
        "data": {
            "id": "043w-058y",
            "source": "043w",
            "target": "058y",
            "width": 0.34657359027997264
        }
    },
    {
        "data": {
            "id": "043w-062p",
            "source": "043w",
            "target": "062p",
            "width": 5.739978979847989
        }
    },
    {
        "data": {
            "id": "043w-033p",
            "source": "043w",
            "target": "033p",
            "width": 2.418140953475739
        }
    },
    {
        "data": {
            "id": "043w-044p",
            "source": "043w",
            "target": "044p",
            "width": 1.6094379124341003
        }
    },
    {
        "data": {
            "id": "043w-050g",
            "source": "043w",
            "target": "050g",
            "width": 5.634406803609911
        }
    },
    {
        "data": {
            "id": "070y-054w",
            "source": "070y",
            "target": "054w",
            "width": 5.577868051513477
        }
    },
    {
        "data": {
            "id": "070y-049p",
            "source": "070y",
            "target": "049p",
            "width": 5.704975494671199
        }
    },
    {
        "data": {
            "id": "070y-018p",
            "source": "070y",
            "target": "018p",
            "width": 5.213486352624437
        }
    },
    {
        "data": {
            "id": "070y-024y",
            "source": "070y",
            "target": "024y",
            "width": 4.568723523227929
        }
    },
    {
        "data": {
            "id": "070y-056b",
            "source": "070y",
            "target": "056b",
            "width": 4.237142845202481
        }
    },
    {
        "data": {
            "id": "070y-014p",
            "source": "070y",
            "target": "014p",
            "width": 1.0986122886681098
        }
    },
    {
        "data": {
            "id": "070y-020p",
            "source": "070y",
            "target": "020p",
            "width": 5.391619386809667
        }
    },
    {
        "data": {
            "id": "070y-008p",
            "source": "070y",
            "target": "008p",
            "width": 2.970085626360216
        }
    },
    {
        "data": {
            "id": "062p-049y",
            "source": "062p",
            "target": "049y",
            "width": 0.6931471805599453
        }
    },
    {
        "data": {
            "id": "062p-043p",
            "source": "062p",
            "target": "043p",
            "width": 2.452637389219215
        }
    },
    {
        "data": {
            "id": "062p-063p",
            "source": "062p",
            "target": "063p",
            "width": 6.088967741140439
        }
    },
    {
        "data": {
            "id": "062p-033p",
            "source": "062p",
            "target": "033p",
            "width": 2.5619819897016294
        }
    },
    {
        "data": {
            "id": "062p-046p",
            "source": "062p",
            "target": "046p",
            "width": 2.271647391135002
        }
    },
    {
        "data": {
            "id": "062p-050g",
            "source": "062p",
            "target": "050g",
            "width": 5.681126863301199
        }
    },
    {
        "data": {
            "id": "031y-032y",
            "source": "031y",
            "target": "032y",
            "width": 3.097202695552336
        }
    },
    {
        "data": {
            "id": "031y-103w",
            "source": "031y",
            "target": "103w",
            "width": 4.983489325158663
        }
    },
    {
        "data": {
            "id": "015p-040r",
            "source": "015p",
            "target": "040r",
            "width": 5.323556973104682
        }
    },
    {
        "data": {
            "id": "015p-052w",
            "source": "015p",
            "target": "052w",
            "width": 5.458043982273845
        }
    },
    {
        "data": {
            "id": "015p-011y",
            "source": "015p",
            "target": "011y",
            "width": 5.564608478131851
        }
    },
    {
        "data": {
            "id": "015p-014p",
            "source": "015p",
            "target": "014p",
            "width": 6.311640927131045
        }
    },
    {
        "data": {
            "id": "015p-009p",
            "source": "015p",
            "target": "009p",
            "width": 6.098321664462754
        }
    },
    {
        "data": {
            "id": "015p-046p",
            "source": "015p",
            "target": "046p",
            "width": 4.5590577139668325
        }
    },
    {
        "data": {
            "id": "015p-045p",
            "source": "015p",
            "target": "045p",
            "width": 3.633762713914086
        }
    },
    {
        "data": {
            "id": "015p-020y",
            "source": "015p",
            "target": "020y",
            "width": 2.6806460828547127
        }
    },
    {
        "data": {
            "id": "033p-050y",
            "source": "033p",
            "target": "050y",
            "width": 5.362107036171247
        }
    },
    {
        "data": {
            "id": "033p-049y",
            "source": "033p",
            "target": "049y",
            "width": 5.502879901017862
        }
    },
    {
        "data": {
            "id": "033p-034p",
            "source": "033p",
            "target": "034p",
            "width": 5.489952677847235
        }
    },
    {
        "data": {
            "id": "033p-067y",
            "source": "033p",
            "target": "067y",
            "width": 5.023425847421999
        }
    },
    {
        "data": {
            "id": "033p-063p",
            "source": "033p",
            "target": "063p",
            "width": 2.317364494114818
        }
    },
    {
        "data": {
            "id": "049p-054w",
            "source": "049p",
            "target": "054w",
            "width": 5.24640041467543
        }
    },
    {
        "data": {
            "id": "049p-024y",
            "source": "049p",
            "target": "024y",
            "width": 4.428330468508625
        }
    },
    {
        "data": {
            "id": "049p-056b",
            "source": "049p",
            "target": "056b",
            "width": 2.24431818486607
        }
    },
    {
        "data": {
            "id": "049p-020p",
            "source": "049p",
            "target": "020p",
            "width": 5.271735634990003
        }
    },
    {
        "data": {
            "id": "049p-008p",
            "source": "049p",
            "target": "008p",
            "width": 3.3631167011793734
        }
    },
    {
        "data": {
            "id": "009p-040r",
            "source": "009p",
            "target": "040r",
            "width": 5.855215578544612
        }
    },
    {
        "data": {
            "id": "009p-052w",
            "source": "009p",
            "target": "052w",
            "width": 5.252163769905444
        }
    },
    {
        "data": {
            "id": "009p-011y",
            "source": "009p",
            "target": "011y",
            "width": 5.769725271954791
        }
    },
    {
        "data": {
            "id": "009p-014p",
            "source": "009p",
            "target": "014p",
            "width": 6.0307892620181125
        }
    },
    {
        "data": {
            "id": "009p-045p",
            "source": "009p",
            "target": "045p",
            "width": 3.4642689090823326
        }
    },
    {
        "data": {
            "id": "009p-020y",
            "source": "009p",
            "target": "020y",
            "width": 2.381086967398878
        }
    },
    {
        "data": {
            "id": "049y-050y",
            "source": "049y",
            "target": "050y",
            "width": 5.29801727651202
        }
    },
    {
        "data": {
            "id": "049y-034p",
            "source": "049y",
            "target": "034p",
            "width": 5.365309574045233
        }
    },
    {
        "data": {
            "id": "049y-067y",
            "source": "049y",
            "target": "067y",
            "width": 5.510746944155437
        }
    },
    {
        "data": {
            "id": "024y-040r",
            "source": "024y",
            "target": "040r",
            "width": 0.5493061443340549
        }
    },
    {
        "data": {
            "id": "024y-052w",
            "source": "024y",
            "target": "052w",
            "width": 1.629048269010741
        }
    },
    {
        "data": {
            "id": "024y-054w",
            "source": "024y",
            "target": "054w",
            "width": 4.375341517392296
        }
    },
    {
        "data": {
            "id": "024y-056b",
            "source": "024y",
            "target": "056b",
            "width": 4.658969191287101
        }
    },
    {
        "data": {
            "id": "024y-020p",
            "source": "024y",
            "target": "020p",
            "width": 4.581047529674094
        }
    },
    {
        "data": {
            "id": "024y-008p",
            "source": "024y",
            "target": "008p",
            "width": 2.6566029895208936
        }
    },
    {
        "data": {
            "id": "024y-020y",
            "source": "024y",
            "target": "020y",
            "width": 1.9143206982445475
        }
    },
    {
        "data": {
            "id": "013p-045p",
            "source": "013p",
            "target": "045p",
            "width": 4.267221772411382
        }
    },
    {
        "data": {
            "id": "013p-052w",
            "source": "013p",
            "target": "052w",
            "width": 2.4599904629140625
        }
    },
    {
        "data": {
            "id": "013p-020y",
            "source": "013p",
            "target": "020y",
            "width": 4.089179082802918
        }
    },
    {
        "data": {
            "id": "011y-040r",
            "source": "011y",
            "target": "040r",
            "width": 6.017010090330433
        }
    },
    {
        "data": {
            "id": "011y-052w",
            "source": "011y",
            "target": "052w",
            "width": 5.50769720442112
        }
    },
    {
        "data": {
            "id": "011y-018p",
            "source": "011y",
            "target": "018p",
            "width": 1.9356005054539456
        }
    },
    {
        "data": {
            "id": "011y-045p",
            "source": "011y",
            "target": "045p",
            "width": 2.11705325229863
        }
    },
    {
        "data": {
            "id": "011y-014p",
            "source": "011y",
            "target": "014p",
            "width": 5.993799710620351
        }
    },
    {
        "data": {
            "id": "011y-046p",
            "source": "011y",
            "target": "046p",
            "width": 5.444530890164265
        }
    },
    {
        "data": {
            "id": "011y-020y",
            "source": "011y",
            "target": "020y",
            "width": 3.8317038324467396
        }
    },
    {
        "data": {
            "id": "049w-054w",
            "source": "049w",
            "target": "054w",
            "width": 0.34657359027997264
        }
    },
    {
        "data": {
            "id": "049w-032y",
            "source": "049w",
            "target": "032y",
            "width": 3.870766794640914
        }
    },
    {
        "data": {
            "id": "049w-046p",
            "source": "049w",
            "target": "046p",
            "width": 4.540229725560831
        }
    },
    {
        "data": {
            "id": "049w-008p",
            "source": "049w",
            "target": "008p",
            "width": 5.240148763362307
        }
    },
    {
        "data": {
            "id": "049w-103w",
            "source": "049w",
            "target": "103w",
            "width": 3.6787781004551765
        }
    },
    {
        "data": {
            "id": "054w-056b",
            "source": "054w",
            "target": "056b",
            "width": 2.389561746555765
        }
    },
    {
        "data": {
            "id": "054w-020p",
            "source": "054w",
            "target": "020p",
            "width": 3.480173864550654
        }
    },
    {
        "data": {
            "id": "054w-058y",
            "source": "054w",
            "target": "058y",
            "width": 2.2154083994216567
        }
    },
    {
        "data": {
            "id": "054w-008p",
            "source": "054w",
            "target": "008p",
            "width": 5.011878192463536
        }
    },
    {
        "data": {
            "id": "063p-043p",
            "source": "063p",
            "target": "043p",
            "width": 0.34657359027997264
        }
    },
    {
        "data": {
            "id": "063p-044p",
            "source": "063p",
            "target": "044p",
            "width": 1.0397207708399179
        }
    },
    {
        "data": {
            "id": "063p-050g",
            "source": "063p",
            "target": "050g",
            "width": 5.4914330260444695
        }
    },
    {
        "data": {
            "id": "050y-067y",
            "source": "050y",
            "target": "067y",
            "width": 4.522024816127378
        }
    },
    {
        "data": {
            "id": "050y-034p",
            "source": "050y",
            "target": "034p",
            "width": 5.03903545661748
        }
    },
    {
        "data": {
            "id": "040r-052w",
            "source": "040r",
            "target": "052w",
            "width": 4.953839378577298
        }
    },
    {
        "data": {
            "id": "040r-014p",
            "source": "040r",
            "target": "014p",
            "width": 5.804504036823636
        }
    },
    {
        "data": {
            "id": "040r-046p",
            "source": "040r",
            "target": "046p",
            "width": 5.638379997652078
        }
    },
    {
        "data": {
            "id": "040r-020y",
            "source": "040r",
            "target": "020y",
            "width": 2.5407021824922316
        }
    },
    {
        "data": {
            "id": "034p-067y",
            "source": "034p",
            "target": "067y",
            "width": 5.140876370358819
        }
    },
    {
        "data": {
            "id": "052w-018p",
            "source": "052w",
            "target": "018p",
            "width": 0.8047189562170501
        }
    },
    {
        "data": {
            "id": "052w-045p",
            "source": "052w",
            "target": "045p",
            "width": 4.538518762330881
        }
    },
    {
        "data": {
            "id": "052w-014p",
            "source": "052w",
            "target": "014p",
            "width": 5.554639351334424
        }
    },
    {
        "data": {
            "id": "052w-046p",
            "source": "052w",
            "target": "046p",
            "width": 4.4020124512065895
        }
    },
    {
        "data": {
            "id": "052w-020y",
            "source": "052w",
            "target": "020y",
            "width": 5.43055607395163
        }
    },
    {
        "data": {
            "id": "052w-008p",
            "source": "052w",
            "target": "008p",
            "width": 2.3853423122328326
        }
    },
    {
        "data": {
            "id": "018p-056b",
            "source": "018p",
            "target": "056b",
            "width": 4.5057007546793955
        }
    },
    {
        "data": {
            "id": "018p-020p",
            "source": "018p",
            "target": "020p",
            "width": 3.844685553764845
        }
    },
    {
        "data": {
            "id": "018p-008p",
            "source": "018p",
            "target": "008p",
            "width": 2.4672369665653457
        }
    },
    {
        "data": {
            "id": "044p-043p",
            "source": "044p",
            "target": "043p",
            "width": 5.764551942848845
        }
    },
    {
        "data": {
            "id": "044p-061y",
            "source": "044p",
            "target": "061y",
            "width": 5.198969931092087
        }
    },
    {
        "data": {
            "id": "044p-058y",
            "source": "044p",
            "target": "058y",
            "width": 5.41341666944198
        }
    },
    {
        "data": {
            "id": "044p-008p",
            "source": "044p",
            "target": "008p",
            "width": 1.4978661367769954
        }
    },
    {
        "data": {
            "id": "032y-103w",
            "source": "032y",
            "target": "103w",
            "width": 4.361371437164699
        }
    },
    {
        "data": {
            "id": "056b-020p",
            "source": "056b",
            "target": "020p",
            "width": 5.8674421574013405
        }
    },
    {
        "data": {
            "id": "056b-046p",
            "source": "056b",
            "target": "046p",
            "width": 0.5493061443340549
        }
    },
    {
        "data": {
            "id": "014p-046p",
            "source": "014p",
            "target": "046p",
            "width": 5.074078867197309
        }
    },
    {
        "data": {
            "id": "014p-045p",
            "source": "014p",
            "target": "045p",
            "width": 3.7206601948588087
        }
    },
    {
        "data": {
            "id": "014p-020y",
            "source": "014p",
            "target": "020y",
            "width": 2.3317195470560335
        }
    },
    {
        "data": {
            "id": "061y-043p",
            "source": "061y",
            "target": "043p",
            "width": 5.544856907187046
        }
    },
    {
        "data": {
            "id": "061y-058y",
            "source": "061y",
            "target": "058y",
            "width": 5.569145097827252
        }
    },
    {
        "data": {
            "id": "061y-046p",
            "source": "061y",
            "target": "046p",
            "width": 2.983073369561846
        }
    },
    {
        "data": {
            "id": "061y-050g",
            "source": "061y",
            "target": "050g",
            "width": 2.2033596236321267
        }
    },
    {
        "data": {
            "id": "020p-008p",
            "source": "020p",
            "target": "008p",
            "width": 1.7328679513998633
        }
    },
    {
        "data": {
            "id": "043p-058y",
            "source": "043p",
            "target": "058y",
            "width": 5.8546858979047895
        }
    },
    {
        "data": {
            "id": "043p-046p",
            "source": "043p",
            "target": "046p",
            "width": 2.6566029895208936
        }
    },
    {
        "data": {
            "id": "058y-046p",
            "source": "058y",
            "target": "046p",
            "width": 2.178354413344796
        }
    },
    {
        "data": {
            "id": "046p-008p",
            "source": "046p",
            "target": "008p",
            "width": 6.144813819718591
        }
    },
    {
        "data": {
            "id": "046p-020y",
            "source": "046p",
            "target": "020y",
            "width": 2.6566029895208936
        }
    },
    {
        "data": {
            "id": "045p-020y",
            "source": "045p",
            "target": "020y",
            "width": 5.055636890764648
        }
    }
],
"nodes": [
    {
        "data": {
            "background_color": "#ffff00",
            "border_color": "#ff0000",
            "border_width": 2,
            "content": "010y",
            "height": 59.39562756799563,
            "id": "010y",
            "popup": "Size is:\t59.395627568\nGroup is:\t1\nInfection Status:\tP",
            "width": 59.39562756799563
        }
    },
    {
        "data": {
            "background_color": "#ffff00",
            "border_color": "#00ff00",
            "border_width": 2,
            "content": "035p",
            "height": 62.33797892203381,
            "id": "035p",
            "popup": "Size is:\t62.337978922\nGroup is:\t1\nInfection Status:\tN",
            "width": 62.33797892203381
        }
    },
    {
        "data": {
            "background_color": "#ff0066",
            "border_color": "#ff0000",
            "border_width": 2,
            "content": "035r",
            "height": 37.09416891226257,
            "id": "035r",
            "popup": "Size is:\t37.0941689123\nGroup is:\t8\nInfection Status:\tP",
            "width": 37.09416891226257
        }
    },
    {
        "data": {
            "background_color": "#00ffff",
            "border_color": "#ff0000",
            "border_width": 2,
            "content": "047p",
            "height": 67.18439231945354,
            "id": "047p",
            "popup": "Size is:\t67.1843923195\nGroup is:\t5\nInfection Status:\tP",
            "width": 67.18439231945354
        }
    },
    {
        "data": {
            "background_color": "#ffff00",
            "border_color": "#00ff00",
            "border_width": 2,
            "content": "064p",
            "height": 50.777558723767626,
            "id": "064p",
            "popup": "Size is:\t50.7775587238\nGroup is:\t1\nInfection Status:\tN",
            "width": 50.777558723767626
        }
    },
    {
        "data": {
            "background_color": "#ffff00",
            "border_color": "#00ff00",
            "border_width": 2,
            "content": "038p",
            "height": 64.90489136674022,
            "id": "038p",
            "popup": "Size is:\t64.9048913667\nGroup is:\t1\nInfection Status:\tN",
            "width": 64.90489136674022
        }
    },
    {
        "data": {
            "background_color": "#ffff00",
            "border_color": "#00ff00",
            "border_width": 2,
            "content": "043p",
            "height": 65.56964993456923,
            "id": "043p",
            "popup": "Size is:\t65.5696499346\nGroup is:\t1\nInfection Status:\tN",
            "width": 65.56964993456923
        }
    },
    {
        "data": {
            "background_color": "#ffff00",
            "border_color": "#00ff00",
            "border_width": 2,
            "content": "016p",
            "height": 59.814668083222855,
            "id": "016p",
            "popup": "Size is:\t59.8146680832\nGroup is:\t1\nInfection Status:\tN",
            "width": 59.814668083222855
        }
    },
    {
        "data": {
            "background_color": "#0000ff",
            "border_color": "#ff0000",
            "border_width": 2,
            "content": "043w",
            "height": 57.054913489612815,
            "id": "043w",
            "popup": "Size is:\t57.0549134896\nGroup is:\t4\nInfection Status:\tP",
            "width": 57.054913489612815
        }
    },
    {
        "data": {
            "background_color": "#ffff00",
            "border_color": "#00ff00",
            "border_width": 2,
            "content": "061y",
            "height": 58.50612800895256,
            "id": "061y",
            "popup": "Size is:\t58.506128009\nGroup is:\t1\nInfection Status:\tN",
            "width": 58.50612800895256
        }
    },
    {
        "data": {
            "background_color": "#ffff00",
            "border_color": "#00ff00",
            "border_width": 2,
            "content": "058y",
            "height": 63.50353033098631,
            "id": "058y",
            "popup": "Size is:\t63.503530331\nGroup is:\t1\nInfection Status:\tN",
            "width": 63.50353033098631
        }
    },
    {
        "data": {
            "background_color": "#ffff00",
            "border_color": "#00ff00",
            "border_width": 2,
            "content": "044p",
            "height": 54.79604487680283,
            "id": "044p",
            "popup": "Size is:\t54.7960448768\nGroup is:\t1\nInfection Status:\tN",
            "width": 54.79604487680283
        }
    },
    {
        "data": {
            "background_color": "#ff0000",
            "border_color": "#ff0000",
            "border_width": 2,
            "content": "038r",
            "height": 36.293993365878364,
            "id": "038r",
            "popup": "Size is:\t36.2939933659\nGroup is:\t3\nInfection Status:\tP",
            "width": 36.293993365878364
        }
    },
    {
        "data": {
            "background_color": "#000000",
            "border_color": "#ff0000",
            "border_width": 2,
            "color": "#ffffff",
            "content": "040r",
            "height": 62.606267453200715,
            "id": "040r",
            "popup": "Size is:\t62.6062674532\nGroup is:\t7\nInfection Status:\tP",
            "width": 62.606267453200715
        }
    },
    {
        "data": {
            "background_color": "#000000",
            "border_color": "#ff0000",
            "border_width": 2,
            "color": "#ffffff",
            "content": "052w",
            "height": 60.91542161445795,
            "id": "052w",
            "popup": "Size is:\t60.9154216145\nGroup is:\t7\nInfection Status:\tP",
            "width": 60.91542161445795
        }
    },
    {
        "data": {
            "background_color": "#ff0000",
            "border_color": "#00ff00",
            "border_width": 2,
            "content": "051p",
            "height": 29.520073627672303,
            "id": "051p",
            "popup": "Size is:\t29.5200736277\nGroup is:\t3\nInfection Status:\tN",
            "width": 29.520073627672303
        }
    },
    {
        "data": {
            "background_color": "#ff0000",
            "border_color": "#00ff00",
            "border_width": 2,
            "content": "013p",
            "height": 19.20604201281128,
            "id": "013p",
            "popup": "Size is:\t19.2060420128\nGroup is:\t3\nInfection Status:\tN",
            "width": 19.20604201281128
        }
    },
    {
        "data": {
            "background_color": "#ff0000",
            "border_color": "#ff0000",
            "border_width": 2,
            "content": "020y",
            "height": 56.10489740431792,
            "id": "020y",
            "popup": "Size is:\t56.1048974043\nGroup is:\t3\nInfection Status:\tP",
            "width": 56.10489740431792
        }
    },
    {
        "data": {
            "background_color": "#ff0000",
            "border_color": "#00ff00",
            "border_width": 2,
            "content": "045p",
            "height": 49.376064694699345,
            "id": "045p",
            "popup": "Size is:\t49.3760646947\nGroup is:\t3\nInfection Status:\tN",
            "width": 49.376064694699345
        }
    },
    {
        "data": {
            "background_color": "#00ffff",
            "border_color": "#ff0000",
            "border_width": 2,
            "content": "046p",
            "height": 69.07755278982137,
            "id": "046p",
            "popup": "Size is:\t69.0775527898\nGroup is:\t5\nInfection Status:\tP",
            "width": 69.07755278982137
        }
    },
    {
        "data": {
            "background_color": "#00ffff",
            "border_color": "#ff0000",
            "border_width": 2,
            "content": "008p",
            "height": 68.83336812470966,
            "id": "008p",
            "popup": "Size is:\t68.8333681247\nGroup is:\t5\nInfection Status:\tP",
            "width": 68.83336812470966
        }
    },
    {
        "data": {
            "background_color": "#ff0066",
            "border_color": "#00ff00",
            "border_width": 2,
            "content": "048p",
            "height": 61.65334881437702,
            "id": "048p",
            "popup": "Size is:\t61.6533488144\nGroup is:\t8\nInfection Status:\tN",
            "width": 61.65334881437702
        }
    },
    {
        "data": {
            "background_color": "#000000",
            "border_color": "#00ff00",
            "border_width": 2,
            "color": "#ffffff",
            "content": "011y",
            "height": 63.47656812833612,
            "id": "011y",
            "popup": "Size is:\t63.4765681283\nGroup is:\t7\nInfection Status:\tN",
            "width": 63.47656812833612
        }
    },
    {
        "data": {
            "background_color": "#ff0066",
            "border_color": "#00ff00",
            "border_width": 2,
            "content": "018p",
            "height": 52.34881156217165,
            "id": "018p",
            "popup": "Size is:\t52.3488115622\nGroup is:\t8\nInfection Status:\tN",
            "width": 52.34881156217165
        }
    },
    {
        "data": {
            "background_color": "#ff0066",
            "border_color": "#00ff00",
            "border_width": 2,
            "content": "037w",
            "height": 62.8791856829303,
            "id": "037w",
            "popup": "Size is:\t62.8791856829\nGroup is:\t8\nInfection Status:\tN",
            "width": 62.8791856829303
        }
    },
    {
        "data": {
            "background_color": "#ff0066",
            "border_color": "#00ff00",
            "border_width": 2,
            "content": "024y",
            "height": 48.88922018115947,
            "id": "024y",
            "popup": "Size is:\t48.8892201812\nGroup is:\t8\nInfection Status:\tN",
            "width": 48.88922018115947
        }
    },
    {
        "data": {
            "background_color": "#ff0066",
            "border_color": "#00ff00",
            "border_width": 2,
            "content": "049p",
            "height": 61.8301599109858,
            "id": "049p",
            "popup": "Size is:\t61.830159911\nGroup is:\t8\nInfection Status:\tN",
            "width": 61.8301599109858
        }
    },
    {
        "data": {
            "background_color": "#ff0066",
            "border_color": "#ff0000",
            "border_width": 2,
            "content": "070y",
            "height": 61.836885416047885,
            "id": "070y",
            "popup": "Size is:\t61.836885416\nGroup is:\t8\nInfection Status:\tP",
            "width": 61.836885416047885
        }
    },
    {
        "data": {
            "background_color": "#ff0066",
            "border_color": "#ff0000",
            "border_width": 2,
            "content": "012b",
            "height": 51.34334402678577,
            "id": "012b",
            "popup": "Size is:\t51.3433440268\nGroup is:\t8\nInfection Status:\tP",
            "width": 51.34334402678577
        }
    },
    {
        "data": {
            "background_color": "#ff0066",
            "border_color": "#00ff00",
            "border_width": 2,
            "content": "020p",
            "height": 58.77907636559541,
            "id": "020p",
            "popup": "Size is:\t58.7790763656\nGroup is:\t8\nInfection Status:\tN",
            "width": 58.77907636559541
        }
    },
    {
        "data": {
            "background_color": "#ff0066",
            "border_color": "#00ff00",
            "border_width": 2,
            "content": "054w",
            "height": 64.18802906256684,
            "id": "054w",
            "popup": "Size is:\t64.1880290626\nGroup is:\t8\nInfection Status:\tN",
            "width": 64.18802906256684
        }
    },
    {
        "data": {
            "background_color": "#0000ff",
            "border_color": "#00ff00",
            "border_width": 2,
            "content": "063p",
            "height": 56.808936231062205,
            "id": "063p",
            "popup": "Size is:\t56.8089362311\nGroup is:\t4\nInfection Status:\tN",
            "width": 56.808936231062205
        }
    },
    {
        "data": {
            "background_color": "#ff0000",
            "border_color": "#00ff00",
            "border_width": 2,
            "content": "010p",
            "height": 38.899659849868506,
            "id": "010p",
            "popup": "Size is:\t38.8996598499\nGroup is:\t3\nInfection Status:\tN",
            "width": 38.899659849868506
        }
    },
    {
        "data": {
            "background_color": "#000000",
            "border_color": "#00ff00",
            "border_width": 2,
            "color": "#ffffff",
            "content": "009p",
            "height": 60.48786792334673,
            "id": "009p",
            "popup": "Size is:\t60.4878679233\nGroup is:\t7\nInfection Status:\tN",
            "width": 60.48786792334673
        }
    },
    {
        "data": {
            "background_color": "#ff0066",
            "border_color": "#ff0000",
            "border_width": 2,
            "content": "056b",
            "height": 57.34018710779232,
            "id": "056b",
            "popup": "Size is:\t57.3401871078\nGroup is:\t8\nInfection Status:\tP",
            "width": 57.34018710779232
        }
    },
    {
        "data": {
            "background_color": "#ff0066",
            "border_color": "#00ff00",
            "border_width": 2,
            "content": "055b",
            "height": 56.153212711723945,
            "id": "055b",
            "popup": "Size is:\t56.1532127117\nGroup is:\t8\nInfection Status:\tN",
            "width": 56.153212711723945
        }
    },
    {
        "data": {
            "background_color": "#000000",
            "border_color": "#00ff00",
            "border_width": 2,
            "color": "#ffffff",
            "content": "067p",
            "height": 22.489255880736515,
            "id": "067p",
            "popup": "Size is:\t22.4892558807\nGroup is:\t7\nInfection Status:\tN",
            "width": 22.489255880736515
        }
    },
    {
        "data": {
            "background_color": "#000000",
            "border_color": "#00ff00",
            "border_width": 2,
            "color": "#ffffff",
            "content": "014p",
            "height": 62.6205676289413,
            "id": "014p",
            "popup": "Size is:\t62.6205676289\nGroup is:\t7\nInfection Status:\tN",
            "width": 62.6205676289413
        }
    },
    {
        "data": {
            "background_color": "#000000",
            "border_color": "#00ff00",
            "border_width": 2,
            "color": "#ffffff",
            "content": "015p",
            "height": 60.495344797883696,
            "id": "015p",
            "popup": "Size is:\t60.4953447979\nGroup is:\t7\nInfection Status:\tN",
            "width": 60.495344797883696
        }
    },
    {
        "data": {
            "background_color": "#0000ff",
            "border_color": "#ff0000",
            "border_width": 2,
            "content": "050g",
            "height": 49.4562314638869,
            "id": "050g",
            "popup": "Size is:\t49.4562314639\nGroup is:\t4\nInfection Status:\tP",
            "width": 49.4562314638869
        }
    },
    {
        "data": {
            "background_color": "#00ffff",
            "border_color": "#00ff00",
            "border_width": 2,
            "content": "049w",
            "height": 46.9572490453124,
            "id": "049w",
            "popup": "Size is:\t46.9572490453\nGroup is:\t5\nInfection Status:\tN",
            "width": 46.9572490453124
        }
    },
    {
        "data": {
            "background_color": "#00ff00",
            "border_color": "#ff0000",
            "border_width": 2,
            "content": "103w",
            "height": 47.04143687697916,
            "id": "103w",
            "popup": "Size is:\t47.041436877\nGroup is:\t2\nInfection Status:\tP",
            "width": 47.04143687697916
        }
    },
    {
        "data": {
            "background_color": "#0000ff",
            "border_color": "#ff0000",
            "border_width": 2,
            "content": "082w",
            "height": 50.83043812636717,
            "id": "082w",
            "popup": "Size is:\t50.8304381264\nGroup is:\t4\nInfection Status:\tP",
            "width": 50.83043812636717
        }
    },
    {
        "data": {
            "background_color": "#ff00ff",
            "border_color": "#ff0000",
            "border_width": 2,
            "content": "050y",
            "height": 12.375752884142756,
            "id": "050y",
            "popup": "Size is:\t12.3757528841\nGroup is:\t6\nInfection Status:\tP",
            "width": 12.375752884142756
        }
    },
    {
        "data": {
            "background_color": "#ff00ff",
            "border_color": "#ff0000",
            "border_width": 2,
            "content": "034p",
            "height": 41.426087669402975,
            "id": "034p",
            "popup": "Size is:\t41.4260876694\nGroup is:\t6\nInfection Status:\tP",
            "width": 41.426087669402975
        }
    },
    {
        "data": {
            "background_color": "#ff00ff",
            "border_color": "#00ff00",
            "border_width": 2,
            "content": "067y",
            "height": 47.855946107719035,
            "id": "067y",
            "popup": "Size is:\t47.8559461077\nGroup is:\t6\nInfection Status:\tN",
            "width": 47.855946107719035
        }
    },
    {
        "data": {
            "background_color": "#0000ff",
            "border_color": "#00ff00",
            "border_width": 2,
            "content": "062p",
            "height": 61.51601252327878,
            "id": "062p",
            "popup": "Size is:\t61.5160125233\nGroup is:\t4\nInfection Status:\tN",
            "width": 61.51601252327878
        }
    },
    {
        "data": {
            "background_color": "#ff00ff",
            "border_color": "#ff0000",
            "border_width": 2,
            "content": "033p",
            "height": 54.67219291846547,
            "id": "033p",
            "popup": "Size is:\t54.6721929185\nGroup is:\t6\nInfection Status:\tP",
            "width": 54.67219291846547
        }
    },
    {
        "data": {
            "background_color": "#ff00ff",
            "border_color": "#00ff00",
            "border_width": 2,
            "content": "049y",
            "height": 51.361501691335704,
            "id": "049y",
            "popup": "Size is:\t51.3615016913\nGroup is:\t6\nInfection Status:\tN",
            "width": 51.361501691335704
        }
    },
    {
        "data": {
            "background_color": "#00ff00",
            "border_color": "#ff0000",
            "border_width": 2,
            "content": "031y",
            "height": 27.779222531340718,
            "id": "031y",
            "popup": "Size is:\t27.7792225313\nGroup is:\t2\nInfection Status:\tP",
            "width": 27.779222531340718
        }
    },
    {
        "data": {
            "background_color": "#00ff00",
            "border_color": "#ff0000",
            "border_width": 2,
            "content": "032y",
            "height": 41.25145797838065,
            "id": "032y",
            "popup": "Size is:\t41.2514579784\nGroup is:\t2\nInfection Status:\tP",
            "width": 41.25145797838065
        }
    }
]
},
"metadata": {
"description": "Desc.",
"tags": [
    ""
],
"title": "Webber-Style-SAVE"
}
}
